anjia_test/__init__.py
anjia_test/cli.py
anjia_test/utils/__init__.py
anjia_test/utils/config.py
anjia_test/utils/default_config.yaml
anjia_test/utils/logger_config.py
anjia_test/utils/notify_wx.py
anjia_test/utils/time_count.py
anjia_test/utils/time_statistic.py
anjia_test-1.0.8.dist-info/licenses/LICENSE
anjia_test-1.0.8.dist-info/METADATA
anjia_test-1.0.8.dist-info/WHEEL
anjia_test-1.0.8.dist-info/entry_points.txt
anjia_test-1.0.8.dist-info/top_level.txt
anjia_test-1.0.8.dist-info/RECORD
