Metadata-Version: 2.4
Name: anjia-test
Version: 1.0.8
Summary: 摄像头小程序实时预览出图时间统计工具
Author: mofanx
License: MIT License
Project-URL: Homepage, https://gitee.com/yanwuning/anjia_test
Requires-Python: >=3.9
License-File: LICENSE
Requires-Dist: uiautomator2>=3.2.0
Requires-Dist: Pillow>=11.3.0
Requires-Dist: requests>=2.32.0
Requires-Dist: loguru>=0.7.0
Requires-Dist: PyYAML>=6.0.0
Dynamic: license-file
